LICENSE
MANIFEST.in
README.rst
setup.py
Pynamixel/__init__.py
Pynamixel/bus.py
Pynamixel/system.py
Pynamixel/tests.py
Pynamixel.egg-info/PKG-INFO
Pynamixel.egg-info/SOURCES.txt
Pynamixel.egg-info/dependency_links.txt
Pynamixel.egg-info/requires.txt
Pynamixel.egg-info/top_level.txt
Pynamixel/concepts/__init__.py
Pynamixel/concepts/joint.py
Pynamixel/concepts/tests.py
Pynamixel/devices/__init__.py
Pynamixel/devices/ax_12.py
Pynamixel/devices/ax_s1.py
Pynamixel/devices/fields.py
Pynamixel/examples/__init__.py
Pynamixel/examples/spider.py
Pynamixel/hardwares/__init__.py
Pynamixel/hardwares/usb2ax.py
Pynamixel/instructions/__init__.py
Pynamixel/instructions/action.py
Pynamixel/instructions/bus_tests.py
Pynamixel/instructions/ping.py
Pynamixel/instructions/read_data.py
Pynamixel/instructions/reg_write.py
Pynamixel/instructions/reset.py
Pynamixel/instructions/sync_write.py
Pynamixel/instructions/tests.py
Pynamixel/instructions/write_data.py