Metadata-Version: 1.1
Name: Pynamixel
Version: 0.1.0
Summary: Library to use Dynamixel servos supporting several hardwares
Home-page: http://pythonhosted.org/Pynamixel
Author: Vincent Jacques
Author-email: vincent@vincent-jacques.net
License: MIT
Platform: UNKNOWN
Classifier: Development Status :: 3 - Alpha
Classifier: Intended Audience :: Developers
Classifier: Intended Audience :: Science/Research
Classifier: License :: OSI Approved
Classifier: License :: OSI Approved :: MIT License
Classifier: Operating System :: OS Independent
Classifier: Programming Language :: Python
Classifier: Programming Language :: Python :: 2
Classifier: Programming Language :: Python :: 2.7
Classifier: Programming Language :: Python :: 3
Classifier: Programming Language :: Python :: 3.4
Classifier: Topic :: Communications
Classifier: Topic :: Education
Classifier: Topic :: Scientific/Engineering
